{
    "maze": {
        "size": { "width": 10, "depth": 10 },
        "map": [
            [ 3, 2, 2, 2, 2, 2, 3, 2, 2, 2, 1 ],
            [ 1, 0, 0, 0, 0, 0, 1, 0, 0, 0, 1 ],
            [ 1, 0, 0, 0, 0, 0, 1, 0, 0, 0, 1 ],
            [ 1, 0, 0, 0, 0, 0, 2, 2, 4, 2, 1 ],
            [ 11, 0, 0, 0, 0, 0, 0, 0, 0, 0, 1 ],
            [ 1, 0, 0, 8, 0, 0, 0, 0, 0, 0, 11 ],
            [ 1, 0, 0, 0, 0, 0, 0, 0, 0, 0, 1 ],
            [ 1, 0, 9, 0, 7, 0, 0, 0, 0, 0, 1 ],
            [ 1, 0, 0, 0, 0, 0, 0, 0, 0, 0, 11 ],
            [ 1, 0, 0, 6, 0, 0, 0, 0, 0, 0, 1 ],
            [ 2, 2, 2, 2, 2, 2, 2, 2, 10, 2, 0 ]

        ],
        "exitLocation": [9.5, 9.0]
    },
    "ground": {
        "size": { "width": 10.0, "height": 0.0625, "depth": 10.0 },
        "segments": { "width": 1, "height": 1, "depth": 1 },
        "primaryColor": "0xffffff",
        "maps": {
            "color": {
                "url": "../../assets/3d/textures/floor/Substance_Graph_BaseColor.jpg"
            },
            "ao": {
                "url": "../../assets/3d/textures/floor/Substance_Graph_AmbientOcclusion.jpg",
                "intensity": 1.0
            },
            "displacement": {
                "url": "",
                "scale": 1.0,
                "bias": 0.0
            },
            "normal": {
                "url": "../../assets/3d/textures/floor/Substance_Graph_Normal.png",
                "type": 0,
                "scale": { "x": 2.0, "y": 2.0 }
            },
            "bump": {
                "url": "",
                "scale": 1.0
            },
            "roughness": {
                "url": "../../assets/3d/textures/floor/Substance_Graph_Roughness.jpg",
                "rough": 1.0
            }
        },
        "wrapS": 1,
        "wrapT": 1,
        "repeat": { "u": 4.0, "v": 4.0 },
        "magFilter": 1,
        "minFilter": 5,
        "secondaryColor": "0x6b554b"
    },
    "wall": {
        "segments": { "width": 1, "height": 1.788 },
        "primaryColor": "0xffffff",
        "maps": {
            "color": {
                "url": "../../assets/3d/textures/concrete_0007_2k_xtGY5J/concrete_0007_color_2k.jpg"
            },
            "ao": {
                "url": "../../assets/3d/textures/concrete_0007_2k_xtGY5J/concrete_0007_ao_2k.jpg",
                "intensity": 1.0
            },
            "displacement": {
                "url": "",
                "scale": 1.0,
                "bias": 0.0
            },
            "normal": {
                "url": "../../assets/3d/textures/concrete_0007_2k_xtGY5J/concrete_0007_normal_opengl_2k.png",
                "type": 0,
                "scale": { "x": 2.0, "y": 2.0 }
                },
            "bump": {
                "url": "",
                "scale": 1.0
            },
            "roughness": {
                "url": "../../assets/3d/textures/concrete_0007_2k_xtGY5J/concrete_0007_roughness_2k.jpg",
                "rough": 1.0
            }
        },
        "wrapS": 1,
        "wrapT": 0,
        "repeat": { "u": 2.0, "v": 1.0 },
        "magFilter": 1,
        "minFilter": 5,
        "secondaryColor": "0x6b554b"
    },
    "tunnel": {
        "segments": { "width": 1, "height": 1.788 },
        "primaryColor": "0xffffff",
        "maps": {
            "color": {
                "url": "../../assets/3d/textures/tunnel/tunnel2.jpg"
            },
            "ao": {
                "url": "../../assets/3d/textures/tunnel/tunnel2.jpg",
                "intensity": 1.0
            },
            "displacement": {
                "url": "",
                "scale": 1.0,
                "bias": 0.0
            },
            "normal": {
                "url": "../../assets/3d/textures/tunnel/tunnel2.jpg",
                "type": 0,
                "scale": { "x": 2.0, "y": 2.0 }
                },
            "bump": {
                "url": "",
                "scale": 1.0
            },
            "roughness": {
                "url": "../../assets/3d/textures/tunnel/tunnel2.jpg",
                "rough": 1.0
            }
        },
        "wrapS": 1,
        "wrapT": 0,
        "repeat": { "u": 1.0, "v": 1.0 },
        "magFilter": 1,
        "minFilter": 5,
        "secondaryColor": "0x6b554b"
    },
    "player": {
        "initialPosition": [4.0, 2.0],
        "initialDirection": 0.0
    },
    "door": {
        "segments": {
            "doorSize": {"width": 0.95, "height": 1.686, "depth": 0.035, "gap": 0.0465 },
            "frameSize": {"width": 1, "height": 1.788, "depth": 0.045}
        },
        "primaryColor": "0xffffff",
        "mapDoor": {
            "door_front": {
                "url": "../../assets/3d/textures/door/door_front.png"
            },
            "door_back": {
                "url": "../../assets/3d/textures/door/door_back.png"
            }
        },
        "mapFrame": {
            "frame_front": {
                "url": "../../assets/3d/textures/door/frame_front.png"
            },
            "frame_back": {
                "url": "../../assets/3d/textures/door/frame_back.png"
            }
        },
        "secondaryColor": "0xc36e2d"
    },
    "elevator": {
        "segments": {
            "elevatorSize": {"width": 1.0, "height": 1.78, "depth": 1.0 }
        },
        "materialParameters":{
            "color": "95949aff",
            "mapElevator": {
                "elevator_closed": {
                    "url": "../../assets/3d/textures/elevator/elevator_closed.jpg"
                },
                "elevator_open": {
                    "url": "../../assets/3d/textures/elevator/elevator_open.jpg"
                }
            }
        }
    }
}